{
    "sw": {
        "appName": "StikaZangu",
        "homeButton": "Nyumbani",
        "english": "English",
        "swahili": "Swahili",
        "explainerWelcome": "Karibu StikaZangu!",
        "explainerSubtitle": "Studio Yako Binafsi ya Stika za AI",
        "explainerIntroTitle": "Badilisha picha yoyote kuwa pakiti ya stika za kufurahisha.",
        "explainerIntroP": "Pakia picha ya rafiki, mnyama, au mhusika umpendaye, na ruhusu AI yetu ikutengenezee seti nzima ya stika maalum. Ni haraka, rahisi, na ina ubunifu usio na mwisho!",
        "getStartedButton": "Tengeneza Stika Sasa",
        "howItWorksTitle": "Inavyofanya Kazi kwa Hatua 4 Rahisi",
        "step1Title": "Pakia Picha Yako",
        "step1P": "Chagua picha iliyo wazi ya mtu, mnyama, au mhusika. Unaweza kuikata ili iwe kamili.",
        "step2Title": "Binafsisha",
        "step2P": "Chagua mtindo wa kisanii, chagua rangi ya usuli, au uifanye iwe wazi.",
        "step3Title": "Ongeza Misemo",
        "step3P": "Tumia misemo yetu ya kawaida kama \"Nzuri sana\" au ongeza yako mwenyewe.",
        "step4Title": "Tengeneza na Pakua",
        "step4P": "Bofya \"Tengeneza\" na uone maajabu. Pakua stika moja kwa moja au kama faili ya .zip.",
        "featuresTitle": "Vipengele Muhimu",
        "featureAI": "✨ <strong>Uzalishaji kwa AI:</strong> Inatumia Gemini ya Google kuunda stika za ubora wa juu.",
        "featureStyles": "🎨 <strong>Mitindo Mbalimbali ya Kisanii:</strong> Chagua kutoka Uhalisia, Uhuishaji, au Muundo wa 3D.",
        "featureCrop": "✂️ <strong>Ukataji Picha Rahisi:</strong> Lenga hasa unachotaka kwenye stika yako.",
        "featureTransparency": "👻 <strong>Uwazi wa Hali ya Juu:</strong> Mfumo wetu huondoa usuli wa miraba kwa uwazi halisi.",
        "featureCustomize": "✏️ <strong>Inabadilishwa Kikamilifu:</strong> Ongeza, ondoa, na hariri misemo ili kuunda pakiti kamilifu.",
        "featureSave": "💾 <strong>Hifadhi Kipindi Chako:</strong> Mipangilio na misemo yako huhifadhiwa kwenye kivinjari chako.",
        "featureBulk": "📦 <strong>Upakuaji wa Pamoja:</strong> Pata stika zako zote kwenye faili moja ya .zip.",
        "creatorTitle": "Studio Yako Binafsi ya Stika",
        "creatorHowItWorks": "Inavyofanya kazi:",
        "creatorStep1": "<span>Pakia, bandika, au piga picha</span> ya mtu, mnyama, au mhusika.",
        "creatorStep2": "<span>Chagua mtindo</span> na chaguzi za usuli.",
        "creatorStep3": "<span>Tengeneza Stika</span> na uangalie AI ikitengeneza pakiti ya kipekee!",
        "uploadPlaceholder": "Gusa ili upakie, piga picha, au ubandike picha (Ctrl+V)",
        "artisticStyleLabel": "Mtindo wa Kisanii",
        "styleRealistic": "Uhalisia",
        "styleAnime": "Uhuishaji",
        "style3d": "Muundo wa 3D",
        "transparentBgLabel": "Usuli Mwangavu",
        "chooseImageButton": "Chagua Picha",
        "changeImageButton": "Badilisha Picha",
        "generateButton": "Tengeneza Stika",
        "generatingButton": "Inatengeneza...",
        "restoreDefaultsButton": "Rejesha Mipangilio",
        "resultsTitle": "Matokeo ya Stika Zako",
        "resultsInfo": "Hizi hapa stika zako. Ongeza zaidi, au zipakue moja kwa moja au zote kwa pamoja!",
        "viewSizeLabel": "Ukubwa:",
        "viewSizeSmall": "Ndogo",
        "viewSizeMedium": "Wastani",
        "viewSizeLarge": "Kubwa",
        "downloadAllButton": "Pakua Zote (.zip)",
        "addExpressionButton": "Ongeza Msemo",
        "addEmotionButton": "Ongeza Hisia",
        "plainEmotionsHeader": "Hisia za Kawaida",
        "expressivePhrasesHeader": "Misemo ya Hisia",
        "expThumbsUp": "Gumba Juu",
        "expCheekySmile": "Tabasamu la Ujanja",
        "expNaughtyWink": "Kukonyeza kwa Utundu",
        "expCoolShades": "Miwani Mipya",
        "expSlowClap": "Makofi ya Polepole",
        "expSadSigh": "Kuhema kwa Huzuni",
        "expFacepalm": "Kujipiga Kofi kwa Kukata Tamaa",
        "expFrown": "Midomo Iliyokunjamana",
        "expTongueOut": "Ulimi Nje",
        "expCuriousThinking": "Kufikiri kwa Udadisi",
        "expPhrasePoapoa": "Poapoa",
        "expPhraseNaijuaHiyo": "Naijua hiyo",
        "expPhraseAchaKabisa": "Acha kabisa",
        "expPhraseNoThanks": "No, Thanks",
        "expPhraseAhsanteSana": "Ahsante sana",
        "expPhraseAaah": "Aaah?!",
        "expPhraseYeeap": "Yeeap",
        "expPhraseUsiogope": "Usiogope",
        "expPhraseUwongo": "Uwongoooooo",
        "expPhraseKausha": "Kausha basi",
        "cropTitle": "Kata Picha Yako",
        "cropInfo": "Chagua sehemu ya picha unayotaka kugeuza kuwa stika.",
        "cancelButton": "Ghairi",
        "cropAndUseButton": "Kata na Tumia",
        "addEmotionTitle": "Ongeza Hisia Mpya",
        "addPhraseTitle": "Ongeza Msemo Mpya",
        "addExpressionLabelPlaceholder": "Kichwa (k.m., Anacheka)",
        "addPhraseEmojiPlaceholder": "Emoji (si lazima)",
        "addButton": "Ongeza",
        "transparencyTitle": "Rekebisha Uwazi",
        "colorToleranceLabel": "Uvumilivu wa Rangi",
        "tileSizeLabel": "Ukubwa wa Kigae",
        "textureProtectionLabel": "Ulinzi wa Umbile",
        "edgeFeatherLabel": "Ulaini wa Ukingo",
        "saveChangesButton": "Hifadhi Mabadiliko",
        "stickerError": "Hitilafu",
        "regenerateTooltip": "Tengeneza Upya",
        "editTransparencyTooltip": "Hariri Uwazi",
        "deleteTooltip": "Futa Msemo",
        "downloadTooltip": "Pakua Stika",
        "chooseSourceTitle": "Chagua Chanzo cha Picha (au bandika na Ctrl+V)",
        "sourceLibrary": "Maktaba ya Picha",
        "sourceCamera": "Tumia Kamera",
        "cameraModalTitle": "Piga Picha",
        "takePictureButton": "Piga Picha",
        "switchCameraButton": "Badilisha Kamera",
        "retakeButton": "Piga Tena",
        "usePictureButton": "Tumia Picha",
        "errorCamera": "Imeshindwa kufikia kamera. Tafadhali angalia ruhusa.",
        "errorInvalidFile": "Tafadhali chagua faili sahihi ya picha (k.m., PNG, JPG, GIF).",
        "errorUploadFirst": "Tafadhali pakia picha kwanza!",
        "errorNeedExpression": "Tafadhali ongeza angalau msemo mmoja ili kutengeneza stika.",
        "errorMajor": "Samahani, hitilafu kubwa imetokea. Tafadhali jaribu tena.",
        "errorExpressionExists": "Msemo wenye jina la \"{label}\" tayari upo.",
        "confirmRestore": "Una uhakika unataka kurejesha misemo na mipangilio yote ya awali? Kitendo hiki kitafuta kipindi chako cha sasa."
    },
    "en": {
        "appName": "StickerMe",
        "homeButton": "Home",
        "english": "English",
        "swahili": "Swahili",
        "explainerWelcome": "Welcome to StickerMe!",
        "explainerSubtitle": "Your Personal AI Sticker Studio",
        "explainerIntroTitle": "Turn any photo into a fun, shareable sticker pack.",
        "explainerIntroP": "Upload a picture of a friend, a pet, or your favorite character, and let our AI generate a whole set of custom stickers for you. It's fast, easy, and endlessly creative!",
        "getStartedButton": "Create Stickers Now",
        "howItWorksTitle": "How It Works in 4 Simple Steps",
        "step1Title": "Upload Your Image",
        "step1P": "Choose a clear photo of a person, pet, or character. You can crop it to perfection.",
        "step2Title": "Customize",
        "step2P": "Select an artistic style, choose a background color, or make it transparent.",
        "step3Title": "Add Expressions",
        "step3P": "Use our default expressions like \"Thumbs up\" or add your own custom ones.",
        "step4Title": "Generate & Download",
        "step4P": "Click \"Generate\" and watch the magic happen. Download stickers one by one or as a .zip file.",
        "featuresTitle": "Key Features",
        "featureAI": "✨ <strong>AI-Powered Generation:</strong> Uses Google's Gemini to create high-quality, expressive stickers.",
        "featureStyles": "🎨 <strong>Multiple Artistic Styles:</strong> Choose from Photo-realistic, Anime, or 3D Render.",
        "featureCrop": "✂️ <strong>Easy Image Cropping:</strong> Focus on exactly what you want in your sticker.",
        "featureTransparency": "👻 <strong>Advanced Transparency:</strong> Our smart algorithm removes checkerboard backgrounds for true transparency.",
        "featureCustomize": "✏️ <strong>Fully Customizable:</strong> Add, remove, and edit expressions to create the perfect pack.",
        "featureSave": "💾 <strong>Save Your Session:</strong> Your settings and expressions are saved in your browser for next time.",
        "featureBulk": "📦 <strong>Bulk Download:</strong> Get all your stickers in a convenient .zip file.",
        "creatorTitle": "Your Personal Sticker Studio",
        "creatorHowItWorks": "How it works:",
        "creatorStep1": "<span>Upload, paste, or take a photo</span> of a person, pet, or character.",
        "creatorStep2": "<span>Choose your style</span> and background options.",
        "creatorStep3": "<span>Generate Stickers</span> and watch the AI create a unique pack!",
        "uploadPlaceholder": "Tap to upload, take a photo, or paste an image (Ctrl+V)",
        "artisticStyleLabel": "Artistic Style",
        "styleRealistic": "Photo-realistic",
        "styleAnime": "Anime",
        "style3d": "3D Render",
        "transparentBgLabel": "Transparent Background",
        "chooseImageButton": "Choose Image",
        "changeImageButton": "Change Image",
        "generateButton": "Generate Stickers",
        "generatingButton": "Generating...",
        "restoreDefaultsButton": "Restore Defaults",
        "resultsTitle": "Your Generated Stickers",
        "resultsInfo": "Here are your generated stickers. Add more, or download them individually or all at once!",
        "viewSizeLabel": "View size:",
        "viewSizeSmall": "Small",
        "viewSizeMedium": "Medium",
        "viewSizeLarge": "Large",
        "downloadAllButton": "Download All (.zip)",
        "addExpressionButton": "Add Expression",
        "addEmotionButton": "Add Emotion",
        "plainEmotionsHeader": "Plain Emotions",
        "expressivePhrasesHeader": "Expressive Phrases",
        "expThumbsUp": "Thumbs up",
        "expCheekySmile": "Cheeky smile",
        "expNaughtyWink": "Naughty wink",
        "expCoolShades": "Cool shades",
        "expSlowClap": "Slow clap",
        "expSadSigh": "Sad sigh",
        "expFacepalm": "Facepalm frustration",
        "expFrown": "Frown lips",
        "expTongueOut": "Tongue out",
        "expCuriousThinking": "Curious thinking",
        "expPhrasePoapoa": "It's all good",
        "expPhraseNaijuaHiyo": "I know that one",
        "expPhraseAchaKabisa": "Absolutely not",
        "expPhraseNoThanks": "No, Thanks",
        "expPhraseAhsanteSana": "Thank you very much",
        "expPhraseAaah": "What?!",
        "expPhraseYeeap": "Yeeap",
        "expPhraseUsiogope": "Don't worry",
        "expPhraseUwongo": "Liiiiies!",
        "expPhraseKausha": "Chill out",
        "cropTitle": "Crop your image",
        "cropInfo": "Select the portion of the image you want to turn into a sticker.",
        "cancelButton": "Cancel",
        "cropAndUseButton": "Crop & Use",
        "addEmotionTitle": "Add New Emotion",
        "addPhraseTitle": "Add New Phrase",
        "addExpressionLabelPlaceholder": "Label (e.g., Laughing)",
        "addPhraseEmojiPlaceholder": "Emoji (optional)",
        "addButton": "Add",
        "transparencyTitle": "Fine-tune Transparency",
        "colorToleranceLabel": "Color Tolerance",
        "tileSizeLabel": "Tile Size",
        "textureProtectionLabel": "Texture Protection",
        "edgeFeatherLabel": "Edge Feather",
        "saveChangesButton": "Save Changes",
        "stickerError": "Error",
        "regenerateTooltip": "Regenerate",
        "editTransparencyTooltip": "Edit Transparency",
        "deleteTooltip": "Delete Expression",
        "downloadTooltip": "Download Sticker",
        "chooseSourceTitle": "Choose Image Source (or paste with Ctrl+V)",
        "sourceLibrary": "Photo Library",
        "sourceCamera": "Use Camera",
        "cameraModalTitle": "Take a Picture",
        "takePictureButton": "Take Picture",
        "switchCameraButton": "Switch Camera",
        "retakeButton": "Retake",
        "usePictureButton": "Use Picture",
        "errorCamera": "Could not access the camera. Please check permissions.",
        "errorInvalidFile": "Please select a valid image file (e.g., PNG, JPG, GIF).",
        "errorUploadFirst": "Please upload an image first!",
        "errorNeedExpression": "Please add at least one expression to generate stickers.",
        "errorMajor": "Sorry, a major error occurred while creating the stickers. Please try again.",
        "errorExpressionExists": "An expression with the label \"{label}\" already exists.",
        "confirmRestore": "Are you sure you want to restore all default expressions and settings? This action will clear your current session."
    }
}